EnvironmentManager-1.0.4.dist-info/DESCRIPTION.rst
EnvironmentManager-1.0.4.dist-info/METADATA
EnvironmentManager-1.0.4.dist-info/RECORD
EnvironmentManager-1.0.4.dist-info/WHEEL
EnvironmentManager-1.0.4.dist-info/metadata.json
EnvironmentManager-1.0.4.dist-info/top_level.txt
environment_manager/__init__.py
environment_manager/config.py
environment_manager/environment_manager.py
environment_manager/os_util.py
