Metadata-Version: 2.0
Name: EnvironmentManager
Version: 1.0.4
Summary: Environment Manager to make it easier to manage python path across different development environments
Home-page: UNKNOWN
Author: Ian Davis
Author-email: thekewlstore@gmail.com
License: UNKNOWN
Platform: UNKNOWN
